ntfy_jupyter/__init__.py
ntfy_jupyter/notify.py
ntfy_jupyter/utils.py
ntfy_jupyter-0.1.1.dist-info/METADATA
ntfy_jupyter-0.1.1.dist-info/WHEEL
ntfy_jupyter-0.1.1.dist-info/entry_points.txt
ntfy_jupyter-0.1.1.dist-info/RECORD
