Metadata-Version: 2.1
Name: ntfy-jupyter
Version: 0.1.1
Summary: 
Author: vali101
Author-email: valentin.peter@hotmail.de
Requires-Python: >=3.10,<4.0
Classifier: Programming Language :: Python :: 3
Classifier: Programming Language :: Python :: 3.10
Classifier: Programming Language :: Python :: 3.11
Requires-Dist: ipython (>=8.26.0,<9.0.0)
Requires-Dist: pytest (>=8.3.2,<9.0.0)
Requires-Dist: requests (>=2.32.3,<3.0.0)
